idor_finder/__init__.py
idor_finder/__main__.py
idor_finder/main.py
idor_finder/core/__init__.py
idor_finder/core/auth_handler.py
idor_finder/core/banner.py
idor_finder/core/config.py
idor_finder/core/crawler.py
idor_finder/core/fuzz_engine.py
idor_finder/core/idor_checker.py
idor_finder/core/matcher.py
idor_finder/core/parameter_extractor.py
idor_finder/core/payload_generator.py
idor_finder/core/report_generator.py
idor_finder/core/utils.py
idor_finder/core/uuid_fuzzer.py
idor_finder/core/plugins/__init__.py
idor_finder/core/plugins/numeric_plugin.py
idor_finder/core/plugins/uuid_plugin.py
idor_finder/data/__init__.py
idor_finder/data/common_payloads.json
idor_finder/data/idor_wordlist.txt
idor_finder/data/sensitive_keywords.txt
idor_finder/examples/__init__.py
idor_finder/examples/config_example.json
idor_finder-0.1.0.dist-info/LICENSE
idor_finder-0.1.0.dist-info/METADATA
idor_finder-0.1.0.dist-info/WHEEL
idor_finder-0.1.0.dist-info/entry_points.txt
idor_finder-0.1.0.dist-info/top_level.txt
idor_finder-0.1.0.dist-info/RECORD
