Metadata-Version: 2.1
Name: idor-finder
Version: 0.1.0
Summary: Powerful IDOR discovery tool with UUID-aware fuzzing and async engine
Home-page: https://github.com/ashutosh0x/idor-finder
Author: Ashutosh Kumar Singh
Author-email: ashutoshkumarsingh0x@gmail.com
License: MIT
Keywords: security,idor,fuzzing,bugbounty,pentest
Classifier: Programming Language :: Python :: 3
Classifier: Programming Language :: Python :: 3 :: Only
Classifier: License :: OSI Approved :: MIT License
Classifier: Operating System :: OS Independent
Classifier: Topic :: Security
Classifier: Development Status :: 4 - Beta
Classifier: Intended Audience :: Information Technology
Classifier: Intended Audience :: System Administrators
License-File: LICENSE
Requires-Dist: httpx==0.27.0
Requires-Dist: beautifulsoup4==4.12.3
Requires-Dist: yarl==1.9.4
Requires-Dist: pydantic>=2.8.2
